mlBlocks/__init__.py
mlBlocks/example.py
blockML-0.0.1.dist-info/LICENSE
blockML-0.0.1.dist-info/METADATA
blockML-0.0.1.dist-info/WHEEL
blockML-0.0.1.dist-info/top_level.txt
blockML-0.0.1.dist-info/RECORD
