Metadata-Version: 2.1
Name: blockML
Version: 0.0.1
Summary: Composite ML Library
Author-email: Mehmet Oktay Ozsoy <mehmet.ozsoy@synnada.ai>
Project-URL: Homepage, https://github.com/synnada-ai/mlBlocks
Project-URL: Issues, https://github.com/synnada-ai/mlBlocks/issues
Classifier: Programming Language :: Python :: 3
Classifier: License :: OSI Approved :: Apache Software License
Classifier: Operating System :: OS Independent
Requires-Python: >=3.10
License-File: LICENSE
